[
    {
      "siape": 2246900,
      "nome": "CARLOS AUGUSTO DE MORAES PIRES",
      "sexo": "MASCULINO",
      "formacao": "DOUTORADO",
      "categoria": "DOCENTE",
      "regime_trabalho": "Dedicação exclusiva",
      "tipo_regime_juridico": "Estatutário",
      "situacao_servidor": "Ativo Permanente",
      "cargo": "PROFESSOR DO MAGISTERIO SUPERIOR",
      "classe_funcional": "Classe E - Titular",
      "unidade": "DEPARTAMENTO DE ENGENHARIA QUÍMICA/ENG",
      "admissao": "10/04/2002"
    },
    {
      "siape": 2199115,
      "nome": "CRISTIANO HORA DE OLIVEIRA FONTES",
      "sexo": "MASCULINO",
      "formacao": "DOUTORADO",
      "categoria": "DOCENTE",
      "regime_trabalho": "Dedicação exclusiva",
      "tipo_regime_juridico": "Estatutário",
      "situacao_servidor": "Ativo Permanente",
      "cargo": "PROFESSOR DO MAGISTERIO SUPERIOR",
      "classe_funcional": "Classe D - Associado",
      "unidade": "DEPARTAMENTO DE ENGENHARIA QUÍMICA/ENG",
      "admissao": "01/10/2004"
    },
    {
      "siape": 2411885,
      "nome": "DANIEL DINIZ SANTANA",
      "sexo": "MASCULINO",
      "formacao": "MESTRADO",
      "categoria": "DOCENTE",
      "regime_trabalho": "20 horas semanais",
      "tipo_regime_juridico": "Estatutário",
      "situacao_servidor": "Ativo Permanente",
      "cargo": "PROFESSOR DO MAGISTERIO SUPERIOR",
      "classe_funcional": "Classe A - Assistente A",
      "unidade": "DEPARTAMENTO DE ENGENHARIA QUÍMICA/ENG",
      "admissao": "09/08/2017"
    },
    {
      "siape": 2539445,
      "nome": "DANIELA ARAUJO COSTA",
      "sexo": "FEMININO",
      "formacao": "MESTRADO",
      "categoria": "DOCENTE",
      "regime_trabalho": "Dedicação exclusiva",
      "tipo_regime_juridico": "Estatutário",
      "situacao_servidor": "Ativo Permanente",
      "cargo": "PROFESSOR DO MAGISTERIO SUPERIOR",
      "classe_funcional": "Classe B - Assistente",
      "unidade": "DEPARTAMENTO DE ENGENHARIA QUÍMICA/ENG",
      "admissao": "08/10/2010"
    },
    {
      "siape": 286723,
      "nome": "EDNILDO ANDRADE TORRES",
      "sexo": "MASCULINO",
      "formacao": "DOUTORADO",
      "categoria": "DOCENTE",
      "regime_trabalho": "Dedicação exclusiva",
      "tipo_regime_juridico": "Estatutário",
      "situacao_servidor": "Ativo Permanente",
      "cargo": "PROFESSOR DO MAGISTERIO SUPERIOR",
      "classe_funcional": "Classe E - Titular",
      "unidade": "DEPARTAMENTO DE ENGENHARIA QUÍMICA/ENG",
      "admissao": "24/03/1987"
    },
    {
      "siape": 1677204,
      "nome": "ELAINE CHRISTINE DE MAGALHAES CABRAL ALBUQUERQUE",
      "sexo": "FEMININO",
      "formacao": "DOUTORADO",
      "categoria": "DOCENTE",
      "regime_trabalho": "Dedicação exclusiva",
      "tipo_regime_juridico": "Estatutário",
      "situacao_servidor": "Ativo Permanente",
      "cargo": "PROFESSOR DO MAGISTERIO SUPERIOR",
      "classe_funcional": "Classe D - Associado",
      "unidade": "DEPARTAMENTO DE ENGENHARIA QUÍMICA/ENG",
      "admissao": "02/02/2009"
    },
    {
      "siape": 3141368,
      "nome": "ERBET ALMEIDA COSTA",
      "sexo": "MASCULINO",
      "formacao": "MESTRADO",
      "categoria": "DOCENTE",
      "regime_trabalho": "20 horas semanais",
      "tipo_regime_juridico": "Estatutário",
      "situacao_servidor": "Ativo Permanente",
      "cargo": "PROFESSOR DO MAGISTERIO SUPERIOR",
      "classe_funcional": "Classe A - Assistente A",
      "unidade": "DEPARTAMENTO DE ENGENHARIA QUÍMICA/ENG",
      "admissao": "06/08/2019"
    },
    {
      "siape": 2367823,
      "nome": "HERBERT PEREIRA DE OLIVEIRA",
      "sexo": "MASCULINO",
      "formacao": "DOUTORADO",
      "categoria": "DOCENTE",
      "regime_trabalho": "20 horas semanais",
      "tipo_regime_juridico": "Estatutário",
      "situacao_servidor": "Ativo Permanente",
      "cargo": "PROFESSOR DO MAGISTERIO SUPERIOR",
      "classe_funcional": "Classe C - Adjunto",
      "unidade": "DEPARTAMENTO DE ENGENHARIA QUÍMICA/ENG",
      "admissao": "30/11/2009"
    },
    {
      "siape": 3495808,
      "nome": "KAREN VALVERDE PONTES",
      "sexo": "FEMININO",
      "formacao": "DOUTORADO",
      "categoria": "DOCENTE",
      "regime_trabalho": "Dedicação exclusiva",
      "tipo_regime_juridico": "Estatutário",
      "situacao_servidor": "Ativo Permanente",
      "cargo": "PROFESSOR DO MAGISTERIO SUPERIOR",
      "classe_funcional": "Classe D - Associado",
      "unidade": "DEPARTAMENTO DE ENGENHARIA QUÍMICA/ENG",
      "admissao": "06/02/2009"
    },
    {
      "siape": 2574950,
      "nome": "KARLA PATRICIA SANTOS OLIVEIRA RODRIGUEZ ESQUERRE",
      "sexo": "FEMININO",
      "formacao": "DOUTORADO",
      "categoria": "DOCENTE",
      "regime_trabalho": "Dedicação exclusiva",
      "tipo_regime_juridico": "Estatutário",
      "situacao_servidor": "Ativo Permanente",
      "cargo": "PROFESSOR DO MAGISTERIO SUPERIOR",
      "classe_funcional": "Classe D - Associado",
      "unidade": "DEPARTAMENTO DE ENGENHARIA QUÍMICA/ENG",
      "admissao": "29/01/2009"
    },
    {
      "siape": 2276528,
      "nome": "LEIZER SCHNITMAN",
      "sexo": "MASCULINO",
      "formacao": "DOUTORADO",
      "categoria": "DOCENTE",
      "regime_trabalho": "Dedicação exclusiva",
      "tipo_regime_juridico": "Estatutário",
      "situacao_servidor": "Ativo Permanente",
      "cargo": "PROFESSOR DO MAGISTERIO SUPERIOR",
      "classe_funcional": "Classe D - Associado",
      "unidade": "DEPARTAMENTO DE ENGENHARIA QUÍMICA/ENG",
      "admissao": "07/02/2007"
    },
    {
      "siape": 2229111,
      "nome": "LUIZ ANTONIO MAGALHAES PONTES",
      "sexo": "MASCULINO",
      "formacao": "DOUTORADO",
      "categoria": "DOCENTE",
      "regime_trabalho": "Dedicação exclusiva",
      "tipo_regime_juridico": "Estatutário",
      "situacao_servidor": "Ativo Permanente",
      "cargo": "PROFESSOR DO MAGISTERIO SUPERIOR",
      "classe_funcional": "Classe C - Adjunto",
      "unidade": "DEPARTAMENTO DE ENGENHARIA QUÍMICA/ENG",
      "admissao": "24/03/2011"
    },
    {
      "siape": 1086477,
      "nome": "MARCELO EMBIRUCU DE SOUZA",
      "sexo": "MASCULINO",
      "formacao": "DOUTORADO",
      "categoria": "DOCENTE",
      "regime_trabalho": "Dedicação exclusiva",
      "tipo_regime_juridico": "Estatutário",
      "situacao_servidor": "Ativo Permanente",
      "cargo": "PROFESSOR DO MAGISTERIO SUPERIOR",
      "classe_funcional": "Classe E - Titular",
      "unidade": "DEPARTAMENTO DE ENGENHARIA QUÍMICA/ENG",
      "admissao": "06/10/1994"
    },
    {
      "siape": 2042153,
      "nome": "MARCIO ANDRE FERNANDES MARTINS",
      "sexo": "MASCULINO",
      "formacao": "DOUTORADO",
      "categoria": "DOCENTE",
      "regime_trabalho": "Dedicação exclusiva",
      "tipo_regime_juridico": "Estatutário",
      "situacao_servidor": "Ativo Permanente",
      "cargo": "PROFESSOR DO MAGISTERIO SUPERIOR",
      "classe_funcional": "Classe C - Adjunto",
      "unidade": "DEPARTAMENTO DE ENGENHARIA QUÍMICA/ENG",
      "admissao": "08/07/2013"
    },
    {
      "siape": 1675191,
      "nome": "MARCIO LUIS FERREIRA NASCIMENTO",
      "sexo": "MASCULINO",
      "formacao": "DOUTORADO",
      "categoria": "DOCENTE",
      "regime_trabalho": "Dedicação exclusiva",
      "tipo_regime_juridico": "Estatutário",
      "situacao_servidor": "Ativo Permanente",
      "cargo": "PROFESSOR DO MAGISTERIO SUPERIOR",
      "classe_funcional": "Classe D - Associado",
      "unidade": "DEPARTAMENTO DE ENGENHARIA QUÍMICA/ENG",
      "admissao": "26/01/2009"
    },
    {
      "siape": 1740886,
      "nome": "MARCOS FABIO DE JESUS",
      "sexo": "MASCULINO",
      "formacao": "MESTRADO",
      "categoria": "DOCENTE",
      "regime_trabalho": "Dedicação exclusiva",
      "tipo_regime_juridico": "Estatutário",
      "situacao_servidor": "Ativo Permanente",
      "cargo": "PROFESSOR DO MAGISTERIO SUPERIOR",
      "classe_funcional": "Classe B - Assistente",
      "unidade": "DEPARTAMENTO DE ENGENHARIA QUÍMICA/ENG",
      "admissao": "30/11/2009"
    },
    {
      "siape": 2042003,
      "nome": "MARCUS VINICIUS AMERICANO DA COSTA FILHO",
      "sexo": "MASCULINO",
      "formacao": "DOUTORADO",
      "categoria": "DOCENTE",
      "regime_trabalho": "Dedicação exclusiva",
      "tipo_regime_juridico": "Estatutário",
      "situacao_servidor": "Ativo Permanente",
      "cargo": "PROFESSOR DO MAGISTERIO SUPERIOR",
      "classe_funcional": "Classe C - Adjunto",
      "unidade": "DEPARTAMENTO DE ENGENHARIA QUÍMICA/ENG",
      "admissao": "09/07/2013"
    },
    {
      "siape": 1853432,
      "nome": "MAURICIO ALVAREZ MUNOZ",
      "sexo": "MASCULINO",
      "formacao": "MESTRADO",
      "categoria": "DOCENTE",
      "regime_trabalho": "20 horas semanais",
      "tipo_regime_juridico": "Estatutário",
      "situacao_servidor": "Ativo Permanente",
      "cargo": "PROFESSOR DO MAGISTERIO SUPERIOR",
      "classe_funcional": "Classe B - Assistente",
      "unidade": "DEPARTAMENTO DE ENGENHARIA QUÍMICA/ENG",
      "admissao": "18/03/2011"
    },
    {
      "siape": 1894417,
      "nome": "MIGUEL ANGEL IGLESIAS DURO",
      "sexo": "MASCULINO",
      "formacao": "DOUTORADO",
      "categoria": "DOCENTE",
      "regime_trabalho": "Dedicação exclusiva",
      "tipo_regime_juridico": "Estatutário",
      "situacao_servidor": "Ativo Permanente",
      "cargo": "PROFESSOR DO MAGISTERIO SUPERIOR",
      "classe_funcional": "Classe C - Adjunto",
      "unidade": "DEPARTAMENTO DE ENGENHARIA QUÍMICA/ENG",
      "admissao": "14/10/2011"
    },
    {
      "siape": 1001821,
      "nome": "RAONY MAIA FONTES",
      "sexo": "MASCULINO",
      "formacao": "MESTRADO",
      "categoria": "DOCENTE",
      "regime_trabalho": "Dedicação exclusiva",
      "tipo_regime_juridico": "Estatutário",
      "situacao_servidor": "Ativo Permanente",
      "cargo": "PROFESSOR DO MAGISTERIO SUPERIOR",
      "classe_funcional": "Classe A - Assistente A",
      "unidade": "DEPARTAMENTO DE ENGENHARIA QUÍMICA/ENG",
      "admissao": "14/04/2016"
    },
    {
      "siape": 1287677,
      "nome": "REGINA FERREIRA VIANNA",
      "sexo": "FEMININO",
      "formacao": "DOUTORADO",
      "categoria": "DOCENTE",
      "regime_trabalho": "Dedicação exclusiva",
      "tipo_regime_juridico": "Estatutário",
      "situacao_servidor": "Ativo Permanente",
      "cargo": "PROFESSOR DO MAGISTERIO SUPERIOR",
      "classe_funcional": "Classe E - Titular",
      "unidade": "DEPARTAMENTO DE ENGENHARIA QUÍMICA/ENG",
      "admissao": "18/08/1998"
    },
    {
      "siape": 1568172,
      "nome": "ROSANA LOPES LIMA FIALHO",
      "sexo": "FEMININO",
      "formacao": "DOUTORADO",
      "categoria": "DOCENTE",
      "regime_trabalho": "Dedicação exclusiva",
      "tipo_regime_juridico": "Estatutário",
      "situacao_servidor": "Ativo Permanente",
      "cargo": "PROFESSOR DO MAGISTERIO SUPERIOR",
      "classe_funcional": "Classe D - Associado",
      "unidade": "DEPARTAMENTO DE ENGENHARIA QUÍMICA/ENG",
      "admissao": "02/04/2007"
    },
    {
      "siape": 2420792,
      "nome": "RUY CARVALHO DE BARROS",
      "sexo": "MASCULINO",
      "formacao": "MESTRADO",
      "categoria": "DOCENTE",
      "regime_trabalho": "20 horas semanais",
      "tipo_regime_juridico": "Estatutário",
      "situacao_servidor": "Ativo Permanente",
      "cargo": "PROFESSOR DO MAGISTERIO SUPERIOR",
      "classe_funcional": "Classe A - Assistente A",
      "unidade": "DEPARTAMENTO DE ENGENHARIA QUÍMICA/ENG",
      "admissao": "15/09/2017"
    },
    {
      "siape": 1215117,
      "nome": "SAMUEL LUPORINI",
      "sexo": "MASCULINO",
      "formacao": "DOUTORADO",
      "categoria": "DOCENTE",
      "regime_trabalho": "Dedicação exclusiva",
      "tipo_regime_juridico": "Estatutário",
      "situacao_servidor": "Ativo Permanente",
      "cargo": "PROFESSOR DO MAGISTERIO SUPERIOR",
      "classe_funcional": "Classe D - Associado",
      "unidade": "DEPARTAMENTO DE ENGENHARIA QUÍMICA/ENG",
      "admissao": "17/12/1996"
    },
    {
      "siape": 1091039,
      "nome": "SILVANA MATTEDI E SILVA",
      "sexo": "FEMININO",
      "formacao": "DOUTORADO",
      "categoria": "DOCENTE",
      "regime_trabalho": "Dedicação exclusiva",
      "tipo_regime_juridico": "Estatutário",
      "situacao_servidor": "Ativo Permanente",
      "cargo": "PROFESSOR DO MAGISTERIO SUPERIOR",
      "classe_funcional": "Classe E - Titular",
      "unidade": "DEPARTAMENTO DE ENGENHARIA QUÍMICA/ENG",
      "admissao": "18/11/1994"
    },
    {
      "siape": 1523793,
      "nome": "SILVIO ALEXANDRE BEISL VIEIRA DE MELO",
      "sexo": "MASCULINO",
      "formacao": "DOUTORADO",
      "categoria": "DOCENTE",
      "regime_trabalho": "Dedicação exclusiva",
      "tipo_regime_juridico": "Estatutário",
      "situacao_servidor": "Ativo Permanente",
      "cargo": "PROFESSOR DO MAGISTERIO SUPERIOR",
      "classe_funcional": "Classe D - Associado",
      "unidade": "DEPARTAMENTO DE ENGENHARIA QUÍMICA/ENG",
      "admissao": "09/03/2006"
    },
    {
      "siape": 2718348,
      "nome": "YURI GUERRIERI PEREIRA",
      "sexo": "MASCULINO",
      "formacao": "MESTRADO",
      "categoria": "DOCENTE",
      "regime_trabalho": "Dedicação exclusiva",
      "tipo_regime_juridico": "Estatutário",
      "situacao_servidor": "Ativo Permanente",
      "cargo": "PROFESSOR DO MAGISTERIO SUPERIOR",
      "classe_funcional": "Classe B - Assistente",
      "unidade": "DEPARTAMENTO DE ENGENHARIA QUÍMICA/ENG",
      "admissao": "27/11/2009"
    }
  ]